expreess/__init__.py
expreess/main.py
expreess/y.py
expreess-0.2.3.dist-info/licenses/LICENSE
expreess-0.2.3.dist-info/METADATA
expreess-0.2.3.dist-info/WHEEL
expreess-0.2.3.dist-info/top_level.txt
expreess-0.2.3.dist-info/RECORD
